lambda_otel_logging/__init__.py
lambda_otel_logging/_version.py
lambda_otel_logging/logging.py
lambda_otel_logging/py.typed
lambda_otel_logging-1.0.0.dist-info/METADATA
lambda_otel_logging-1.0.0.dist-info/WHEEL
lambda_otel_logging-1.0.0.dist-info/licenses/LICENSE
lambda_otel_logging-1.0.0.dist-info/RECORD
