Metadata-Version: 2.4
Name: lambda-otel-logging
Version: 1.0.0
Summary: Python logging formatter that looks like OpenTelemetry logs
Author-email: Bram Neijt <bram@neijt.nl>
License-File: LICENSE
Classifier: Intended Audience :: Developers
Classifier: License :: OSI Approved :: Apache Software License
Classifier: Programming Language :: Python :: 3
Requires-Python: >=3.10
Requires-Dist: msgspec>=0.17.0
Requires-Dist: opentelemetry-sdk>=1.20.0
